pfctl/__init__.py
pfctl/pfctl.py
pfctl-0.0.3.dist-info/LICENSE
pfctl-0.0.3.dist-info/METADATA
pfctl-0.0.3.dist-info/WHEEL
pfctl-0.0.3.dist-info/top_level.txt
pfctl-0.0.3.dist-info/RECORD
