Metadata-Version: 2.1
Name: pfctl
Version: 0.0.3
Summary: Python framework for creating third-party libraries
Home-page: https://github.com/vtongxue/pfctl
Author: student_v
Author-email: 13974164156@163.com
Project-URL: Bug tracker, https://github.com/vtongxue/pfctl/issues
Classifier: Development Status :: 3 - Alpha
Classifier: Programming Language :: Python :: 3
Classifier: License :: OSI Approved :: MIT License
Classifier: Operating System :: OS Independent
Requires-Python: >=3.6
License-File: LICENSE
Requires-Dist: setuptools
